panda3d_logos/__init__.py
panda3d_logos/panda3dsplash.py
panda3d_logos/splashes.py
panda3d_logos/assets/__init__.py
panda3d_logos/assets/panda3d_logo.bam
panda3d_logos/assets/panda3d_logo.blend
panda3d_logos/assets/panda3d_logo.frag
panda3d_logos/assets/panda3d_logo.png
panda3d_logos/assets/panda3d_logo.psd
panda3d_logos/assets/panda3d_logo.svg
panda3d_logos/assets/panda3d_logo.vert
panda3d_logos/assets/panda3d_logo.wav
panda3d_logos/assets/panda3d_logo_panda.png
panda3d_logos/assets/splash_window.frag
panda3d_logos/assets/splash_window.vert
panda3d_logos/assets/panda3d_logo_texture/panda3d_logo_texture-base.png
panda3d_logos/assets/panda3d_logo_texture/panda3d_logo_texture-metallic.png
panda3d_logos/assets/panda3d_logo_texture/panda3d_logo_texture-roughness.png
panda3d_logos/assets/panda3d_logo_texture/panda3d_logo_texture-specular.png
panda3d_logos-0.131.dist-info/LICENSE
panda3d_logos-0.131.dist-info/METADATA
panda3d_logos-0.131.dist-info/WHEEL
panda3d_logos-0.131.dist-info/entry_points.txt
panda3d_logos-0.131.dist-info/top_level.txt
panda3d_logos-0.131.dist-info/RECORD
