Metadata-Version: 2.1
Name: panda3d-logos
Version: 0.131
Summary: The Panda3D logo in various formats, a 3d animated splash screen and code to show it off.
Home-page: https://github.com/thecheapestpixels/panda3d-logos
Author: thecheapestpixels
License: UNKNOWN
Keywords: panda3d
Platform: UNKNOWN
License-File: LICENSE
Requires-Dist: panda3d
